{
  "name": "Zephyr Apps",
  "dockerComposeFile": "../compose.yml",
  "service": "zephyr_apps",
  "workspaceFolder": "/workdir",
  "shutdownAction": "stopCompose",
  "remoteUser": "root",
  "privileged": true,
  "customizations": {
    "vscode": {
      "settings": {
        "terminal.integrated.defaultProfile.linux": "bash"
      }
    }
  },
  "mounts": [
    "source=${localEnv:SSH_AUTH_SOCK},target=/ssh-agent,type=bind"
  ],
  "remoteEnv": {
    "SSH_AUTH_SOCK": "/tmp/ssh-XXXXXXn9szK2/agent.35679"
  }
}
